{
    "english_name": "zsq_wsy",
    "chinese_name": "\u81ea\u9501\u5668\u672a\u4f7f\u7528\uff08\u5728\u4eba\u8eab\u4e0a\u672a\u4f7f\u7528\uff09",
    "describe": null,
    "attention": [],
    "pic_describe": [
        [
            "\u6807\u6ce8\u8303\u56f4\uff1a\u81ea\u9501\u5668\u6302\u4ef6\u5230\u4eba\u8170\u90e8\u7684\u8303\u56f4",
            "http://192.168.3.50:11106/customer_file/download/469afbe31df388461428cfdda2795973.png",
            {}
        ]
    ],
    "create_time": "2024-09-09 01:08:16",
    "update_time": "2024-09-09 01:08:16"
}